newtonnet/__init__.py
newtonnet/data/__init__.py
newtonnet/data/loader.py
newtonnet/data/neighbors.py
newtonnet/data/parse_raw.py
newtonnet/layers/__init__.py
newtonnet/layers/activations.py
newtonnet/layers/precision.py
newtonnet/layers/representations.py
newtonnet/layers/scalers.py
newtonnet/models/__init__.py
newtonnet/models/newtonnet.py
newtonnet/models/output.py
newtonnet/train/__init__.py
newtonnet/train/loss.py
newtonnet/train/optimizer.py
newtonnet/train/trainer.py
newtonnet/utils/__init__.py
newtonnet/utils/ase_interface.py
newtonnet/utils/pretrained_models.py
newtonnet-2.0.1.dist-info/METADATA
newtonnet-2.0.1.dist-info/WHEEL
newtonnet-2.0.1.dist-info/top_level.txt
newtonnet-2.0.1.dist-info/RECORD
