Metadata-Version: 2.4
Name: NewtonNet
Version: 2.0.1
Summary: A Newtonian message passing network for deep learning of interatomic potentials and forces
Author-email: Teresa Head-Gordon <thg@berkeley.edu>
License: MIT
Project-URL: repository, https://github.com/THGLab/NewtonNet
Keywords: Machine Learning,Data Mining,Quantum Chemistry,Molecular Dynamics
Classifier: Development Status :: 4 - Beta
Classifier: Natural Language :: English
Classifier: Intended Audience :: Science/Research
Classifier: Programming Language :: Python :: 3
Requires-Dist: numpy<2.0.0
Requires-Dist: scipy
Requires-Dist: scikit-learn
Requires-Dist: pandas
Requires-Dist: ase
Requires-Dist: tqdm
Requires-Dist: pyyaml
Requires-Dist: wandb
Requires-Dist: torch
Requires-Dist: torch_geometric
Requires-Dist: torch_scatter
Requires-Dist: torch_cluster
